{
    "/js/app.js": "/js/app.js",
    "/css/app.css": "/css/app.css",
    "/js/app.fe3df491cafa6c155f34.hot-update.js": "/js/app.fe3df491cafa6c155f34.hot-update.js",
    "/js/app.f70d51480f69dedd9d7b.hot-update.js": "/js/app.f70d51480f69dedd9d7b.hot-update.js",
    "/js/app.efc05a0d97f86fc6e006.hot-update.js": "/js/app.efc05a0d97f86fc6e006.hot-update.js",
    "/js/app.a65f188b5c39dd0340a3.hot-update.js": "/js/app.a65f188b5c39dd0340a3.hot-update.js",
    "/js/app.dab4895b4ebf98f20ba5.hot-update.js": "/js/app.dab4895b4ebf98f20ba5.hot-update.js",
    "/js/app.635f06dc096fbccb5e9d.hot-update.js": "/js/app.635f06dc096fbccb5e9d.hot-update.js",
    "/js/app.a8fa00d188cd1a5a1875.hot-update.js": "/js/app.a8fa00d188cd1a5a1875.hot-update.js",
    "/js/app.198bb6ec4a7f21b0a725.hot-update.js": "/js/app.198bb6ec4a7f21b0a725.hot-update.js",
    "/js/app.6a12e62e710adb5e2ee3.hot-update.js": "/js/app.6a12e62e710adb5e2ee3.hot-update.js",
    "/js/app.3ae896ed2ee5e6529bbe.hot-update.js": "/js/app.3ae896ed2ee5e6529bbe.hot-update.js",
    "/js/app.37c311f144057417e121.hot-update.js": "/js/app.37c311f144057417e121.hot-update.js",
    "/js/app.e8a60fad59019eae3901.hot-update.js": "/js/app.e8a60fad59019eae3901.hot-update.js",
    "/js/app.5fdbc6fe2d9bf63764ce.hot-update.js": "/js/app.5fdbc6fe2d9bf63764ce.hot-update.js",
    "/js/app.2c36e3830f22d39e28bf.hot-update.js": "/js/app.2c36e3830f22d39e28bf.hot-update.js",
    "/js/app.0f8abfad61f2da11efdd.hot-update.js": "/js/app.0f8abfad61f2da11efdd.hot-update.js",
    "/js/app.3de22c133eb48932e51f.hot-update.js": "/js/app.3de22c133eb48932e51f.hot-update.js",
    "/js/app.a7d85673fdda78696437.hot-update.js": "/js/app.a7d85673fdda78696437.hot-update.js",
    "/js/app.b33e594766232e828b2f.hot-update.js": "/js/app.b33e594766232e828b2f.hot-update.js",
    "/js/app.906d1b1fdb0ff3df85fe.hot-update.js": "/js/app.906d1b1fdb0ff3df85fe.hot-update.js",
    "/js/app.53cafde87062a08dba94.hot-update.js": "/js/app.53cafde87062a08dba94.hot-update.js",
    "/js/app.27c020dd23d644f946e5.hot-update.js": "/js/app.27c020dd23d644f946e5.hot-update.js",
    "/js/app.1854409b9c24775a2beb.hot-update.js": "/js/app.1854409b9c24775a2beb.hot-update.js",
    "/js/app.744f2b07cdda0265febc.hot-update.js": "/js/app.744f2b07cdda0265febc.hot-update.js",
    "/js/app.b4196df9b4e454fc2703.hot-update.js": "/js/app.b4196df9b4e454fc2703.hot-update.js",
    "/js/app.12ee8c27b0e012c8c52e.hot-update.js": "/js/app.12ee8c27b0e012c8c52e.hot-update.js",
    "/js/app.0cebed78b68586aedd59.hot-update.js": "/js/app.0cebed78b68586aedd59.hot-update.js",
    "/js/app.9635d081c2706d90a2b2.hot-update.js": "/js/app.9635d081c2706d90a2b2.hot-update.js",
    "/js/app.f557ae7478c82452c5fa.hot-update.js": "/js/app.f557ae7478c82452c5fa.hot-update.js",
    "/js/app.0328df27a0ef09afaf38.hot-update.js": "/js/app.0328df27a0ef09afaf38.hot-update.js",
    "/js/app.77fba469f7e83ab57952.hot-update.js": "/js/app.77fba469f7e83ab57952.hot-update.js",
    "/js/app.1bdfa3ba66ebcb4d029f.hot-update.js": "/js/app.1bdfa3ba66ebcb4d029f.hot-update.js",
    "/js/app.3cae85b4c90f2cb7494e.hot-update.js": "/js/app.3cae85b4c90f2cb7494e.hot-update.js",
    "/js/app.f514afbccb1e1eaa27e2.hot-update.js": "/js/app.f514afbccb1e1eaa27e2.hot-update.js",
    "/js/app.2ecd17e032b331ba3d8f.hot-update.js": "/js/app.2ecd17e032b331ba3d8f.hot-update.js",
    "/js/app.2dd26b0ab559929b3cc0.hot-update.js": "/js/app.2dd26b0ab559929b3cc0.hot-update.js",
    "/js/app.ca2f92d59c5311b0788d.hot-update.js": "/js/app.ca2f92d59c5311b0788d.hot-update.js",
    "/js/app.d14ee413647f225dd2f7.hot-update.js": "/js/app.d14ee413647f225dd2f7.hot-update.js",
    "/js/app.4dec944e7a25d39cf326.hot-update.js": "/js/app.4dec944e7a25d39cf326.hot-update.js",
    "/js/app.85aaa00126f2db93c3de.hot-update.js": "/js/app.85aaa00126f2db93c3de.hot-update.js",
    "/js/app.628c5e604c88baf82e0f.hot-update.js": "/js/app.628c5e604c88baf82e0f.hot-update.js",
    "/js/app.abd94fa1904ac2c3bcc4.hot-update.js": "/js/app.abd94fa1904ac2c3bcc4.hot-update.js",
    "/js/app.fcbc476a00b6367f9408.hot-update.js": "/js/app.fcbc476a00b6367f9408.hot-update.js",
    "/js/app.bc3b30aae02f99328af7.hot-update.js": "/js/app.bc3b30aae02f99328af7.hot-update.js",
    "/js/app.1e6efc1688e0640b5fa6.hot-update.js": "/js/app.1e6efc1688e0640b5fa6.hot-update.js",
    "/js/app.a85459c2562bd2efe53e.hot-update.js": "/js/app.a85459c2562bd2efe53e.hot-update.js",
    "/js/app.8c8b69933bf827797809.hot-update.js": "/js/app.8c8b69933bf827797809.hot-update.js",
    "/js/app.5257f70cce0f2ebf87fd.hot-update.js": "/js/app.5257f70cce0f2ebf87fd.hot-update.js",
    "/js/app.a4998bb7a1a115e40513.hot-update.js": "/js/app.a4998bb7a1a115e40513.hot-update.js",
    "/js/app.5d47598548b8d3b45f72.hot-update.js": "/js/app.5d47598548b8d3b45f72.hot-update.js",
    "/js/app.641b911b4b3d2843a101.hot-update.js": "/js/app.641b911b4b3d2843a101.hot-update.js",
    "/js/app.f396c0f97ac38b9de7c4.hot-update.js": "/js/app.f396c0f97ac38b9de7c4.hot-update.js",
    "/js/app.170a62cac51d67acbf6c.hot-update.js": "/js/app.170a62cac51d67acbf6c.hot-update.js",
    "/js/app.5039d39a06835396af39.hot-update.js": "/js/app.5039d39a06835396af39.hot-update.js",
    "/js/app.4a7ea862ff2cd49a0c09.hot-update.js": "/js/app.4a7ea862ff2cd49a0c09.hot-update.js",
    "/js/app.585c155b35dbf2a106ec.hot-update.js": "/js/app.585c155b35dbf2a106ec.hot-update.js",
    "/js/app.a2f9cd8a1529d8a4e42c.hot-update.js": "/js/app.a2f9cd8a1529d8a4e42c.hot-update.js",
    "/js/app.ea48da7aa53ad6dabf3a.hot-update.js": "/js/app.ea48da7aa53ad6dabf3a.hot-update.js",
    "/js/app.6decc2b33375812b1990.hot-update.js": "/js/app.6decc2b33375812b1990.hot-update.js",
    "/js/app.d6d887448f6791dbe120.hot-update.js": "/js/app.d6d887448f6791dbe120.hot-update.js",
    "/js/app.8cdf9812d81dc54a32a7.hot-update.js": "/js/app.8cdf9812d81dc54a32a7.hot-update.js",
    "/js/app.6f4f3cd64b278478f484.hot-update.js": "/js/app.6f4f3cd64b278478f484.hot-update.js",
    "/js/app.fe01af4e7d0c5e5da62e.hot-update.js": "/js/app.fe01af4e7d0c5e5da62e.hot-update.js",
    "/js/app.f6e83fc6206a2e6cc523.hot-update.js": "/js/app.f6e83fc6206a2e6cc523.hot-update.js",
    "/js/app.77a3933ce02854b507c1.hot-update.js": "/js/app.77a3933ce02854b507c1.hot-update.js",
    "/js/app.d10ab19e751983ec6249.hot-update.js": "/js/app.d10ab19e751983ec6249.hot-update.js",
    "/js/app.e876963323ac37c77987.hot-update.js": "/js/app.e876963323ac37c77987.hot-update.js",
    "/js/app.c31fb967825875cb3841.hot-update.js": "/js/app.c31fb967825875cb3841.hot-update.js",
    "/js/app.dfdf77d23821c563a55a.hot-update.js": "/js/app.dfdf77d23821c563a55a.hot-update.js",
    "/js/app.4cd5cf77a52ce517c80d.hot-update.js": "/js/app.4cd5cf77a52ce517c80d.hot-update.js",
    "/js/app.d7595e3de8d520f72cad.hot-update.js": "/js/app.d7595e3de8d520f72cad.hot-update.js",
    "/js/app.679176ff1ae9d2787473.hot-update.js": "/js/app.679176ff1ae9d2787473.hot-update.js",
    "/js/app.5ad48ce31d7f11fce3fd.hot-update.js": "/js/app.5ad48ce31d7f11fce3fd.hot-update.js",
    "/js/app.27169f3534646c49ff03.hot-update.js": "/js/app.27169f3534646c49ff03.hot-update.js",
    "/js/app.43265b780c7214906b4d.hot-update.js": "/js/app.43265b780c7214906b4d.hot-update.js",
    "/js/app.df34ec4a9e839d81bc7d.hot-update.js": "/js/app.df34ec4a9e839d81bc7d.hot-update.js",
    "/js/app.3a891484dd3555d08779.hot-update.js": "/js/app.3a891484dd3555d08779.hot-update.js",
    "/js/app.5077c268a3cf232c6d52.hot-update.js": "/js/app.5077c268a3cf232c6d52.hot-update.js",
    "/js/app.b4b26de49044d541dd2c.hot-update.js": "/js/app.b4b26de49044d541dd2c.hot-update.js",
    "/js/app.4980f258df5f05289247.hot-update.js": "/js/app.4980f258df5f05289247.hot-update.js",
    "/js/app.851c18035ced515ba023.hot-update.js": "/js/app.851c18035ced515ba023.hot-update.js",
    "/js/app.226cc38e9f775cb6591d.hot-update.js": "/js/app.226cc38e9f775cb6591d.hot-update.js",
    "/js/app.1f8cf5bd77ccfe509a6d.hot-update.js": "/js/app.1f8cf5bd77ccfe509a6d.hot-update.js",
    "/js/app.17ca344becd178525bb8.hot-update.js": "/js/app.17ca344becd178525bb8.hot-update.js",
    "/js/app.ba2f546f70a6be600f8d.hot-update.js": "/js/app.ba2f546f70a6be600f8d.hot-update.js",
    "/js/app.c86435f0842400abc87b.hot-update.js": "/js/app.c86435f0842400abc87b.hot-update.js",
    "/js/app.ba795f3a3c7269de757e.hot-update.js": "/js/app.ba795f3a3c7269de757e.hot-update.js",
    "/js/app.3d2ff8f8959d78d23343.hot-update.js": "/js/app.3d2ff8f8959d78d23343.hot-update.js",
    "/js/app.57707c254dc34ec936d7.hot-update.js": "/js/app.57707c254dc34ec936d7.hot-update.js",
    "/js/app.1d84a275f494d11eab23.hot-update.js": "/js/app.1d84a275f494d11eab23.hot-update.js",
    "/js/app.74924a1d62d48168d555.hot-update.js": "/js/app.74924a1d62d48168d555.hot-update.js",
    "/js/app.d11e179a01c4f8957966.hot-update.js": "/js/app.d11e179a01c4f8957966.hot-update.js",
    "/js/app.c3b5a6ae94452b46d671.hot-update.js": "/js/app.c3b5a6ae94452b46d671.hot-update.js",
    "/js/app.25fa4d40a65d00ee375c.hot-update.js": "/js/app.25fa4d40a65d00ee375c.hot-update.js",
    "/js/app.df8c95c79a969f5b259a.hot-update.js": "/js/app.df8c95c79a969f5b259a.hot-update.js",
    "/js/app.51efd6881d54c669a351.hot-update.js": "/js/app.51efd6881d54c669a351.hot-update.js",
    "/js/app.be3962b8b8d4c9c0ec7f.hot-update.js": "/js/app.be3962b8b8d4c9c0ec7f.hot-update.js",
    "/js/app.1c63ad5de70710a3bcca.hot-update.js": "/js/app.1c63ad5de70710a3bcca.hot-update.js",
    "/js/app.36fd4ee13a8098f2e423.hot-update.js": "/js/app.36fd4ee13a8098f2e423.hot-update.js",
    "/js/app.3b12d198625aa339874d.hot-update.js": "/js/app.3b12d198625aa339874d.hot-update.js",
    "/js/app.ff1c742aa5bc9912abef.hot-update.js": "/js/app.ff1c742aa5bc9912abef.hot-update.js",
    "/js/app.cb059139bad6eeb33932.hot-update.js": "/js/app.cb059139bad6eeb33932.hot-update.js",
    "/js/app.bede1fe51792b8e257e9.hot-update.js": "/js/app.bede1fe51792b8e257e9.hot-update.js",
    "/js/app.ea697b548177dd3e47aa.hot-update.js": "/js/app.ea697b548177dd3e47aa.hot-update.js",
    "/js/app.4439c8b7f1da5e091e71.hot-update.js": "/js/app.4439c8b7f1da5e091e71.hot-update.js",
    "/js/app.2ab1b952df795ea20283.hot-update.js": "/js/app.2ab1b952df795ea20283.hot-update.js",
    "/js/app.634a37c673584200684f.hot-update.js": "/js/app.634a37c673584200684f.hot-update.js",
    "/js/app.3987c2041e4b7b2d3076.hot-update.js": "/js/app.3987c2041e4b7b2d3076.hot-update.js",
    "/js/app.d324b5b2963980c66b72.hot-update.js": "/js/app.d324b5b2963980c66b72.hot-update.js",
    "/js/app.a8e1ce80a4620eb63da2.hot-update.js": "/js/app.a8e1ce80a4620eb63da2.hot-update.js",
    "/js/app.f0987ac3f2d899144477.hot-update.js": "/js/app.f0987ac3f2d899144477.hot-update.js",
    "/js/app.0636c16318ad145d6491.hot-update.js": "/js/app.0636c16318ad145d6491.hot-update.js",
    "/js/app.186c7c9d8255ee8e2d26.hot-update.js": "/js/app.186c7c9d8255ee8e2d26.hot-update.js",
    "/js/app.76451492ef99c684763c.hot-update.js": "/js/app.76451492ef99c684763c.hot-update.js",
    "/js/app.1bf6d4b070d11bf670ad.hot-update.js": "/js/app.1bf6d4b070d11bf670ad.hot-update.js",
    "/js/app.c309ee68c9f332636b7d.hot-update.js": "/js/app.c309ee68c9f332636b7d.hot-update.js",
    "/js/app.6d3f269be205e68fe3b4.hot-update.js": "/js/app.6d3f269be205e68fe3b4.hot-update.js",
    "/js/app.e8e2ddba56c861e858eb.hot-update.js": "/js/app.e8e2ddba56c861e858eb.hot-update.js",
    "/js/app.3b7d5c8802fbff685104.hot-update.js": "/js/app.3b7d5c8802fbff685104.hot-update.js",
    "/js/app.01067e4815d6d98f9b26.hot-update.js": "/js/app.01067e4815d6d98f9b26.hot-update.js",
    "/js/app.451fab0cb69df99c923d.hot-update.js": "/js/app.451fab0cb69df99c923d.hot-update.js",
    "/js/app.f4bbf8a69c83d2e60a46.hot-update.js": "/js/app.f4bbf8a69c83d2e60a46.hot-update.js",
    "/js/app.8decadab7b38f4fc8882.hot-update.js": "/js/app.8decadab7b38f4fc8882.hot-update.js",
    "/js/app.8fa1162a0e9e048743ab.hot-update.js": "/js/app.8fa1162a0e9e048743ab.hot-update.js",
    "/js/app.6a9d117a81cf5cd951bb.hot-update.js": "/js/app.6a9d117a81cf5cd951bb.hot-update.js"
}
